otp_notify/__init__.py
otp_notify/admin.py
otp_notify/conf.py
otp_notify/models.py
otp_notify/tests.py
otp_notify/migrations/0001_initial.py
otp_notify/migrations/__init__.py
django_otp_notify-0.3.0.dist-info/LICENSE
django_otp_notify-0.3.0.dist-info/METADATA
django_otp_notify-0.3.0.dist-info/WHEEL
django_otp_notify-0.3.0.dist-info/top_level.txt
django_otp_notify-0.3.0.dist-info/RECORD
