Metadata-Version: 2.1
Name: django-otp-notify
Version: 0.3.0
Summary: A django-otp plugin that delivers tokens via Notify's SMS service.
Home-page: https://github.com/PierrePaul/django-otp-notify
Author: Pierre-Paul Lefebvre, Peter Sagerson
Author-email: pierre-paul.lefebvre@cds-snc.ca
License: BSD
Project-URL: Documentation, https://django-otp-notify.readthedocs.io/
Project-URL: Source, https://github.com/django-otp/django-otp-notify
Platform: UNKNOWN
Classifier: Development Status :: 5 - Production/Stable
Classifier: Programming Language :: Python :: 3
Classifier: Intended Audience :: Developers
Classifier: License :: OSI Approved :: BSD License
Classifier: Topic :: Security
Classifier: Topic :: Software Development :: Libraries :: Python Modules
Classifier: Framework :: Django
Requires-Dist: django-otp (>=0.9.0)
Requires-Dist: notifications-python-client
